{"zpQAiyMGlk8SqW3OUbpiqg==":"whatsapp-image-2023-10-25-at-8.48.51-am-removebg-preview.png","YxWe4mGaGUEFzKJajQKOoQ==":"whatsapp-image-2023-10-25-at-8.48.51-am-removebg-preview-1.png","JFSHY3RoGDpBQ5lkuMY14g==":"whatsapp-image-2023-10-25-at-8.48.51-am-removebg-preview-2.png","rVaBRBS/CadlgGmyfXDLSg==":"mbr.jpg","JQGInizkp3FPUUtB7wmQ/w==":"mbr-1.jpg","X+AR/5uge6t817HT2lIPAA==":"mbr-2.jpg","3v1w8XKk0AJJMGpHcgyAsQ==":"mbr-3.jpg","v7BHuTqn9VZcdwGZopu63A==":"62-627145-gold-jewellery-hd-2034245466.jpg","N+GR3N9KS4FteWyMaGTiqA==":"3713600-2152289801.jpg","7U4xJJgNJAF93xzC3X5gRw==":"necklace-zoom-dsc-9776.jpg","kO4ydTVLfuz/QqJNjkLX1Q==":"output-onlinepngtools.png","imLPW2wNd1OvPpFIrZFnEg==":"banner1.png","px+yd71P47N4iXs6AQNBfw==":"img.png","MPIwSdANugJ630hFLRZGug==":"banner1-1.png","/iqbyU2pp1+2tKloDLfkFA==":"banner1-2.png","21mFcqoY/g542QbD90BebQ==":"banner1-3.png","vNHxugCdPmMuI+kc53Mpdg==":"banner1-4.png","QHuxLPmhn/igQU5c2qQqQw==":"banner1-5.png","b6ueBiMC5qqf0m7DcPf0wQ==":"beimg.png","b4+gMhXVMZXrzFCUg3M2EA==":"beimg2.png","B0P6NMihMqfIIVkFyJtG1A==":"beimg3.png","M8KWqi4VWiHM6gHjSnZrTg==":"banner2.png","cf2NwbEtbZQKxkCZXGz54A==":"fk-43819.jpg","SKmrhZtGONTuqtLrLhu0Xw==":"er2972-full-gold-jhumki-earring-womens-online-shopping-jewellery-1-425x500.webp","jqyhcB/Y39kv+Sp5pHUm7g==":"cac.png"}